[
  {
    "word": "relativ",
    "japanese": "相対的",
    "related": "ラテン語 relatio (関係) 由来"
  },
  {
    "word": "steuern",
    "japanese": "制御する",
    "related": "Steuer (税金、舵)"
  },
  {
    "word": "sich ergeben (aus + Dativ)",
    "japanese": "（〜から）生じる、明らかになる",
    "related": "geben (与える)"
  },
  {
    "word": "widersprechen (+ Dativ)",
    "japanese": "（～に）反論する、矛盾する",
    "related": "wider (〜に反して), sprechen (話す)"
  },
  {
    "word": "vielleicht",
    "japanese": "もしかしたら",
    "related": "viel (多くの), leicht (容易に)"
  },
  {
    "word": "fordern",
    "japanese": "要求する",
    "related": "die Forderung (要求)"
  },
  {
    "word": "stabil",
    "japanese": "安定した",
    "related": "die Stabilität (安定性)"
  },
  {
    "word": "hochwertig",
    "japanese": "高品質の",
    "related": "hoch (高い), der Wert (価値)"
  },
  {
    "word": "der Wandel, -",
    "japanese": "変化、変遷",
    "related": "wandeln (変える、歩く)"
  },
  {
    "word": "zeugen von",
    "japanese": "~の証拠となる",
    "related": "Zeuge (証人), Zeugnis (証明書)"
  },
  {
    "word": "der Widerspruch, ¨-e",
    "japanese": "矛盾",
    "related": "wider (反対に), Spruch (言葉), sprechen (話す)"
  },
  {
    "word": "die Gesellschaft, -en",
    "japanese": "社会",
    "related": "gesellig (社交的な)"
  },
  {
    "word": "die Sache, -n",
    "japanese": "事、物",
    "related": "sachlich (客観的な)"
  },
  {
    "word": "Stufenordnung",
    "japanese": "段階秩序",
    "related": "die Stufe (段階), die Ordnung (秩序)"
  },
  {
    "word": "allerdings",
    "japanese": "しかしながら、もっとも",
    "related": "alle (全ての), Dinge (事柄)"
  },
  {
    "word": "ableiten",
    "japanese": "導き出す",
    "related": "ab (から), leiten (導く)"
  },
  {
    "word": "beitragen zu",
    "japanese": "~に貢献する",
    "related": "bei (〜へ), tragen (運ぶ、貢献する), der Beitrag (貢献)"
  },
  {
    "word": "maßgeblich",
    "japanese": "決定的に",
    "related": "das Maß (尺度), geben (与える)"
  },
  {
    "word": "gut / schlecht",
    "japanese": "良い / 悪い",
    "related": "das Gut (善、財産), die Güte (良さ) / verschlechtern (悪化させる)"
  },
  {
    "word": "auf dem Vormarsch sein",
    "japanese": "台頭している",
    "related": "vor (前に), der Marsch (行進)"
  },
  {
    "word": "der Unterschied, -e",
    "japanese": "違い、差異",
    "related": "unter (間に), scheiden (分ける)"
  },
  {
    "word": "bestätigen",
    "japanese": "確認する",
    "related": "stätig (一定の), Stadt (都市)"
  },
  {
    "word": "widerlegen",
    "japanese": "～の誤りを証明する、論破する",
    "related": "wider (〜に反して), legen (置く)"
  },
  {
    "word": "die Unterscheidung",
    "japanese": "区別",
    "related": "unterscheiden (区別する), scheiden (分ける)"
  },
  {
    "word": "die Wirklichkeit",
    "japanese": "現実、実在",
    "related": "wirklich (現実の), wirken (作用する)"
  },
  {
    "word": "die Art, -en",
    "japanese": "種類、方法",
    "related": "artig (行儀の良い), unartig (行儀の悪い), eigenartig (独特な)"
  },
  {
    "word": "verweigern",
    "japanese": "拒否する",
    "related": "(語源的に「拒絶する」の意)"
  },
  {
    "word": "befürworten",
    "japanese": "支持する",
    "related": "für (〜のために), das Wort (言葉)"
  },
  {
    "word": "sehr",
    "japanese": "とても",
    "related": "(古高ドイツ語の「痛み」から「程度が甚だしい」へ)"
  },
  {
    "word": "die Diskrepanz, -en",
    "japanese": "食い違い、矛盾、不一致",
    "related": "ラテン語 discrepare (一致しない)"
  },
  {
    "word": "die Verschiedenheit, -en",
    "japanese": "多様性、相違",
    "related": "verschieden (異なる), scheiden (分ける)"
  },
  {
    "word": "die Entsprechung, -en",
    "japanese": "対応、相当",
    "related": "entsprechen (対応する), sprechen (話す)"
  },
  {
    "word": "vielmehr",
    "japanese": "むしろ",
    "related": "viel (より多く), mehr (もっと)"
  },
  {
    "word": "scheitern an",
    "japanese": "~で失敗する",
    "related": "Scheiter (薪)"
  },
  {
    "word": "abgrenzen (von + Dativ)",
    "japanese": "～を（〜から）区別する、境界を引く",
    "related": "die Grenze (境界)"
  },
  {
    "word": "die Stimmung, -en",
    "japanese": "雰囲気、気分",
    "related": "die Stimme (声), stimmen (調和する)"
  },
  {
    "word": "der Grundsatz, ¨-e",
    "japanese": "基本方針、原則",
    "related": "der Grund (基礎), der Satz (文、命題)"
  },
  {
    "word": "damit",
    "japanese": "それによって、そのために",
    "related": "da (それ), mit (〜と)"
  },
  {
    "word": "schließen",
    "japanese": "結論づける",
    "related": "der Schluss (結論), das Schloss (鍵)"
  },
  {
    "word": "die Wirkung, -en",
    "japanese": "作用、効果",
    "related": "wirken (作用する), wirklich (現実の)"
  },
  {
    "word": "vorhersehbar",
    "japanese": "予測可能な",
    "related": "vorher (前に), sehen (見る)"
  },
  {
    "word": "schädlich",
    "japanese": "有害な",
    "related": "Schaden (害)"
  },
  {
    "word": "täuschen",
    "japanese": "だます",
    "related": "Täuschung (騙すこと)"
  },
  {
    "word": "die Grundlage, -n",
    "japanese": "基礎",
    "related": "der Grund (基礎), legen (置く)"
  },
  {
    "word": "entstehen",
    "japanese": "生じる、生成する",
    "related": "stehen (立つ)"
  },
  {
    "word": "sein großer Schüler",
    "japanese": "彼の偉大な弟子",
    "related": "groß (偉大な), der Schüler (弟子), die Schule (学派)"
  },
  {
    "word": "etablieren",
    "japanese": "確立する",
    "related": "das Etablissement (施設)"
  },
  {
    "word": "erobern",
    "japanese": "征服する",
    "related": "(語源的に「支配下に置く」の意)"
  },
  {
    "word": "vorschreiben",
    "japanese": "規定する",
    "related": "vor (前に), schreiben (書く)"
  },
  {
    "word": "das Verfahren,",
    "japanese": "手順、プロセス",
    "related": "verfahren (進める), fahren (進む)"
  },
  {
    "word": "entgegenwirken",
    "japanese": "対抗する",
    "related": "entgegen (反対に), wirken (作用する)"
  },
  {
    "word": "erfassen",
    "japanese": "把握する、記録する",
    "related": "fassen (掴む)"
  },
  {
    "word": "Vernunftglaubens",
    "japanese": "理性信仰",
    "related": "die Vernunft (理性), der Glaube (信仰)"
  },
  {
    "word": "ablehnen",
    "japanese": "～を拒否する、否定する",
    "related": "lehnen (寄りかかる)"
  },
  {
    "word": "die Qual, -en",
    "japanese": "苦痛",
    "related": "quälen (苦しめる)"
  },
  {
    "word": "kompatibel",
    "japanese": "互換性のある",
    "related": "die Kompatibilität (互換性)"
  },
  {
    "word": "daher",
    "japanese": "それゆえに",
    "related": "da (そこ), her (こちらへ)"
  },
  {
    "word": "die Verfassung, -en",
    "japanese": "憲法、（心身の）状態",
    "related": "verfassen (作成する), fassen (掴む)"
  },
  {
    "word": "das Vermögen",
    "japanese": "能力",
    "related": "vermögen (〜できる), mögen (〜かもしれない)"
  },
  {
    "word": "behavioristisch",
    "japanese": "行動主義的な",
    "related": "der Behaviorismus (行動主義)"
  },
  {
    "word": "naturrechtlich",
    "japanese": "自然法上の",
    "related": "das Naturrecht (自然法)"
  },
  {
    "word": "für Kritik sorgen",
    "japanese": "批判を招く",
    "related": "Kritik (批判), Sorge (心配、配慮)"
  },
  {
    "word": "umsetzen",
    "japanese": "実行する、実現する、実践に移す",
    "related": "um (転換), setzen (置く)"
  },
  {
    "word": "berücksichtigen",
    "japanese": "考慮に入れる",
    "related": "Rücksicht (配慮), Rücken (背中), Sicht (視界)"
  },
  {
    "word": "feststellen",
    "japanese": "～を確認する、断定する",
    "related": "fest (固く), stellen (置く)"
  },
  {
    "word": "verfügen über +A",
    "japanese": "~を自由に使える、~を持っている",
    "related": "fügen (合わせる)"
  },
  {
    "word": "unterscheiden",
    "japanese": "区別する",
    "related": "scheiden (分ける)"
  },
  {
    "word": "auf klären über",
    "japanese": "~について説明する、啓蒙する",
    "related": "auf (上に), klar (明るい)"
  },
  {
    "word": "betragen, [a→ä]",
    "japanese": "(数値が) 〜である",
    "related": "tragen (運ぶ、持つ)"
  },
  {
    "word": "der Einwand, ¨-e",
    "japanese": "反論、異議",
    "related": "einwenden (反論する), wenden (向ける)"
  },
  {
    "word": "einschränken",
    "japanese": "制限する",
    "related": "die Schranke (柵、制限)"
  },
  {
    "word": "beruhen (auf + Dativ)",
    "japanese": "～に基づいている",
    "related": "ruhen (休む)"
  },
  {
    "word": "der Fortschritt, -e",
    "japanese": "進歩",
    "related": "fortschreiten (前進する), Schritt (歩み)"
  },
  {
    "word": "Achtung",
    "japanese": "尊敬",
    "related": "achten (尊敬する)"
  },
  {
    "word": "verschwenden",
    "japanese": "浪費する",
    "related": "schwinden (消える)"
  },
  {
    "word": "einschätzen",
    "japanese": "評価する、見積もる",
    "related": "ein (中に), schätzen (評価する), Schatz (宝)"
  },
  {
    "word": "unbewegte Beweger",
    "japanese": "不動の動者",
    "related": "un- (不), bewegen (動かす)"
  },
  {
    "word": "dar|legen",
    "japanese": "説明する、詳述する",
    "related": "dar- (提示), legen (置く)"
  },
  {
    "word": "die Gerechtigkeit",
    "japanese": "正義",
    "related": "gerecht (公正な), Recht (権利、法)"
  },
  {
    "word": "zählen zu",
    "japanese": "~に数えられる",
    "related": "Zahl (数), erzählen (物語る)"
  },
  {
    "word": "minderwertig",
    "japanese": "低品質の",
    "related": "minder (より少なく), Wert (価値)"
  },
  {
    "word": "überlebenswichtig",
    "japanese": "生存に不可欠な",
    "related": "überleben (生き残る), wichtig (重要な)"
  },
  {
    "word": "wichtig / unwichtig",
    "japanese": "重要 / 重要でない",
    "related": "die Wichtigkeit (重要性), das Gewicht (重さ)"
  },
  {
    "word": "verbreiten",
    "japanese": "広める",
    "related": "ver- (広げる), breit (広い)"
  },
  {
    "word": "abwenden",
    "japanese": "回避する",
    "related": "ab (離れて), wenden (向ける)"
  },
  {
    "word": "überlegen sein",
    "japanese": "優れている",
    "related": "überlegen (熟考する), legen (置く)"
  },
  {
    "word": "das Ergebnis, -se",
    "japanese": "結果",
    "related": "sich ergeben (生じる), geben (与える)"
  },
  {
    "word": "zurückführen auf",
    "japanese": "せいにする、還元する、〜に帰する、〜に遡る",
    "related": "zurück (後ろへ), führen (導く)"
  },
  {
    "word": "obwohl",
    "japanese": "～にもかかわらず",
    "related": "ob (〜かどうか), wohl (まあ、元気に)"
  },
  {
    "word": "solide",
    "japanese": "堅実な",
    "related": "die Solidität (堅実さ)"
  },
  {
    "word": "beabsichtigen",
    "japanese": "意図する",
    "related": "Absicht (意図), Sicht (視界)"
  },
  {
    "word": "übersichtlich",
    "japanese": "見やすい、分かりやすい",
    "related": "die Übersicht (概観), die Sicht (視界)"
  },
  {
    "word": "das Grundrecht, -e",
    "japanese": "基本的人権",
    "related": "der Grund (基本), das Recht (権利)"
  },
  {
    "word": "die Zufriedenheit, /",
    "japanese": "満足",
    "related": "zufrieden (満足な), Frieden (平和)"
  },
  {
    "word": "um denken",
    "japanese": "考え直す",
    "related": "um (周りを、転換), denken (考える)"
  },
  {
    "word": "wirtschaftlich",
    "japanese": "経済的な",
    "related": "die Wirtschaft (経済)"
  },
  {
    "word": "die Schlussfolgerung, -en / der Schluss, ¨-e",
    "japanese": "結論",
    "related": "schlussfolgern (結論を出す), folgen (従う), schließen (閉じる、結論づける)"
  },
  {
    "word": "das Versäumnis, -se",
    "japanese": "怠慢、不作為",
    "related": "versäumen (怠る、逃す)"
  },
  {
    "word": "erläutern",
    "japanese": "～を解説する、釈明する",
    "related": "lauter (純粋な、明るい)"
  },
  {
    "word": "einsparen",
    "japanese": "節約する",
    "related": "ein (中に), sparen (節約する)"
  },
  {
    "word": "verdrängen",
    "japanese": "追い出す、取って代わる",
    "related": "drängen (押す)"
  },
  {
    "word": "die Ausbeutung, -en",
    "japanese": "搾取",
    "related": "ausbeuten (搾取する), die Beute (獲物)"
  },
  {
    "word": "bewerten",
    "japanese": "評価する",
    "related": "be- + Wert (価値)"
  },
  {
    "word": "das Beispiel, -e",
    "japanese": "例",
    "related": "bei (〜の際に), das Spiel (例え)"
  },
  {
    "word": "zusammenhängen mit",
    "japanese": "~と関連がある",
    "related": "zusammen (一緒に), hängen (掛かる)"
  },
  {
    "word": "die Verbindung, -en",
    "japanese": "結合、つながり",
    "related": "verbinden (結びつける), binden (結ぶ)"
  },
  {
    "word": "moralische Gesetz",
    "japanese": "道徳法則",
    "related": "die Moral (道徳), das Gesetz (法則)"
  },
  {
    "word": "die Furcht",
    "japanese": "恐怖",
    "related": "fürchten (恐れる)"
  },
  {
    "word": "erwerben, [e→i]",
    "japanese": "取得する",
    "related": "werben (得るために努力する)"
  },
  {
    "word": "überflüssig",
    "japanese": "余分な",
    "related": "über (超えて), der Fluss (流れ)"
  },
  {
    "word": "notwendig",
    "japanese": "必然的な、必要な",
    "related": "die Not (必要), wenden (向ける)"
  },
  {
    "word": "die Gegebenheit, -en",
    "japanese": "与件、事実、状況",
    "related": "geben (与える), gegeben (与えられた)"
  },
  {
    "word": "Vertreter der Stoa",
    "japanese": "ストア派の代表者",
    "related": "vertreten (代表する), die Stoa (ストア派)"
  },
  {
    "word": "überwiegen",
    "japanese": "上回る",
    "related": "über (上に), wiegen (重さがある)"
  },
  {
    "word": "ganz",
    "japanese": "全ての、全く",
    "related": "ergänzen (補う), das Ganze (全体)"
  },
  {
    "word": "die Konvention, -en",
    "japanese": "慣習",
    "related": "konventionell (慣習的な)"
  },
  {
    "word": "die Idee",
    "japanese": "イデア",
    "related": "ideal (理想的な)"
  },
  {
    "word": "antizipieren",
    "japanese": "予測する",
    "related": "ラテン語 ante (前に) + capere (取る)"
  },
  {
    "word": "die Verflechtung, -en",
    "japanese": "絡み合い、連関",
    "related": "verflechten (絡み合わせる), flechten (編む)"
  },
  {
    "word": "der Missstand, e",
    "japanese": "悪弊",
    "related": "miss- (悪い), Stand (状態)"
  },
  {
    "word": "die Verantwortung tragen",
    "japanese": "責任を負う",
    "related": "verantworten (責任を負う), Antwort (答え)"
  },
  {
    "word": "nachgehen (+ Dativ)",
    "japanese": "（問いなど）を追究する",
    "related": "nach (〜の後を), gehen (行く)"
  },
  {
    "word": "renommiert",
    "japanese": "有名な",
    "related": "フランス語 renommé (有名な)"
  },
  {
    "word": "denn",
    "japanese": "というのも〜だからだ",
    "related": "(接続詞として独自の語源)"
  },
  {
    "word": "der Zusammenbruch, -e",
    "japanese": "崩壊",
    "related": "zusammen (一緒に), der Bruch (破壊)"
  },
  {
    "word": "umstritten",
    "japanese": "物議を醸す",
    "related": "um (周りを), streiten (争う), Streit (争い)"
  },
  {
    "word": "der Schaden, -",
    "japanese": "損害",
    "related": "schaden (害する), schädlich (有害な)"
  },
  {
    "word": "die Verknüpfung, -en",
    "japanese": "連結",
    "related": "verknüpfen (結びつける), Knopf (ボタン)"
  },
  {
    "word": "weitreichend",
    "japanese": "広範囲にわたる",
    "related": "weit (遠く), reichen (届く)"
  },
  {
    "word": "integrieren",
    "japanese": "統合する",
    "related": "die Integration (統合)"
  },
  {
    "word": "überwachen",
    "japanese": "監視する",
    "related": "über (上に), wachen (見張る)"
  },
  {
    "word": "das Gleichgewicht, /",
    "japanese": "バランス",
    "related": "gleich (同じ), Gewicht (重さ)"
  },
  {
    "word": "die Trennung, -en",
    "japanese": "分離、区別",
    "related": "trennen (分ける)"
  },
  {
    "word": "dauerhaft",
    "japanese": "永続的な",
    "related": "Dauer (持続), dauern (続く)"
  },
  {
    "word": "Ideenreich",
    "japanese": "イデア界",
    "related": "die Idee (イデア), das Reich (王国)"
  },
  {
    "word": "der Wettbewerb, -e",
    "japanese": "競争",
    "related": "die Wette (賭け), sich bewerben (応募する)"
  },
  {
    "word": "nachweisen",
    "japanese": "証明する",
    "related": "nach (後を追って), weisen (示す), Beweis (証明)"
  },
  {
    "word": "umgangssprachlich",
    "japanese": "口語の",
    "related": "der Umgang (付き合い), die Sprache (言語)"
  },
  {
    "word": "auftreten",
    "japanese": "発生する、登場する",
    "related": "auf (上に), treten (踏む), Auftritt (登場)"
  },
  {
    "word": "die Bedeutung",
    "japanese": "意味、重要性",
    "related": "bedeuten (意味する), deuten (指し示す)"
  },
  {
    "word": "verknüpfen",
    "japanese": "結びつける",
    "related": "Knopf (ボタン)"
  },
  {
    "word": "der Ausgangspunkt, -e",
    "japanese": "出発点",
    "related": "der Ausgang (出口、出発), der Punkt (点)"
  },
  {
    "word": "die Erläuterung, -en",
    "japanese": "解説、釈明",
    "related": "erläutern (解説する), lauter (純粋な)"
  },
  {
    "word": "umfassend",
    "japanese": "包括的な",
    "related": "um (周りを), fassen (掴む)"
  },
  {
    "word": "erforderlich",
    "japanese": "必要な",
    "related": "erfordern (要求する), fordern (要求する)"
  },
  {
    "word": "der Entwurf, -e",
    "japanese": "草案、デザイン案",
    "related": "entwerfen (設計する), werfen (投げる)"
  },
  {
    "word": "ansehen als",
    "japanese": "~とみなす",
    "related": "an (〜を), sehen (見る)"
  },
  {
    "word": "in Beziehung setzen (zu + Dativ)",
    "japanese": "～を（〜と）関係づける",
    "related": "die Beziehung (関係), setzen (置く)"
  },
  {
    "word": "prognostizieren",
    "japanese": "予測する",
    "related": "die Prognose (予測)"
  },
  {
    "word": "sich befassen mit",
    "japanese": "~を扱う、~に取り組む",
    "related": "fassen (掴む、理解する)"
  },
  {
    "word": "aristotelischer Provenienz",
    "japanese": "アリストテレス的起源の",
    "related": "Aristoteles, die Provenienz (由来)"
  },
  {
    "word": "die Wahrheit",
    "japanese": "真理、真実",
    "related": "wahr (真実の)"
  },
  {
    "word": "die Führungskraft,-e",
    "japanese": "指導力、指導的立場にある人",
    "related": "führen (導く), Kraft (力)"
  },
  {
    "word": "entsprechen",
    "japanese": "一致する",
    "related": "ent- (反対), sprechen (話す)"
  },
  {
    "word": "auf greifen",
    "japanese": "取り上げる",
    "related": "auf (上に), greifen (掴む)"
  },
  {
    "word": "pauschal",
    "japanese": "一括の",
    "related": "die Pauschale (一括料金)"
  },
  {
    "word": "veranschaulichen",
    "japanese": "分かりやすく説明する",
    "related": "anschaulich (分かりやすい), schauen (見る)"
  },
  {
    "word": "beherrschen",
    "japanese": "習得する、支配する",
    "related": "der Herr (主人), herrschen (支配する)"
  },
  {
    "word": "wirksam",
    "japanese": "効果的な",
    "related": "wirken (作用する), Wirkung (効果)"
  },
  {
    "word": "grundsätzlich",
    "japanese": "基本的に、根本的に",
    "related": "Grund (基礎), Sache (事柄)"
  },
  {
    "word": "sollen",
    "japanese": "～すべきである",
    "related": "die Schuld (罪、責任)"
  },
  {
    "word": "gefährden",
    "japanese": "危険にさらす",
    "related": "Gefahr (危険), fahren (行く)"
  },
  {
    "word": "die Abgrenzung, -en",
    "japanese": "境界設定、区別",
    "related": "ab (離れて), Grenze (境界)"
  },
  {
    "word": "die Begründung, -en",
    "japanese": "理由付け、正当化",
    "related": "begründen (基礎づける), der Grund (理由)"
  },
  {
    "word": "vorwerfen",
    "japanese": "非難する",
    "related": "vor (前に), werfen (投げる), Vorwurf (非難)"
  },
  {
    "word": "machen",
    "japanese": "する、作る",
    "related": "die Macht (力)"
  },
  {
    "word": "der Vorläufer,",
    "japanese": "先駆け、前身",
    "related": "vor (前に), laufen (走る)"
  },
  {
    "word": "sich durchsetzen gegen",
    "japanese": "~に打ち勝つ、普及する",
    "related": "durch (〜を通り抜けて), setzen (置く)"
  },
  {
    "word": "immanenten, lebendigen Seele",
    "japanese": "内在的で、生き生きとした魂",
    "related": "immanent (内在的な), leben (生きる), die Seele (魂)"
  },
  {
    "word": "neu / alt",
    "japanese": "新しい / 古い",
    "related": "erneuern (新しくする), die Neuigkeit (ニュース) / das Alter (年齢)"
  },
  {
    "word": "die Wechselwirkung, -en",
    "japanese": "相互作用",
    "related": "wechseln (変わる), wirken (作用する)"
  },
  {
    "word": "unterschätzen",
    "japanese": "過小評価する",
    "related": "unter (下に), schätzen (評価する)"
  },
  {
    "word": "entwerfen, [ei]",
    "japanese": "設計する、草案を作成する",
    "related": "werfen (投げる), der Entwurf (草案)"
  },
  {
    "word": "wenn",
    "japanese": "もし～ならば、～のとき",
    "related": "(時間・条件を示す接続詞として独自の語源)"
  },
  {
    "word": "enthalten",
    "japanese": "含む",
    "related": "ent- + halten (保つ)"
  },
  {
    "word": "äußern",
    "japanese": "表明する",
    "related": "außen (外に), Äußerung (発言)"
  },
  {
    "word": "Bezug nehmen auf",
    "japanese": "~に言及する",
    "related": "Bezug (関係), ziehen (引く)"
  },
  {
    "word": "vollständig",
    "japanese": "完全な",
    "related": "voll (満ちた), Stand (状態)"
  },
  {
    "word": "die Quelle, -n",
    "japanese": "情報源",
    "related": "quellen (湧き出る)"
  },
  {
    "word": "überprüfen",
    "japanese": "～を検証する、チェックする",
    "related": "prüfen (試験する)"
  },
  {
    "word": "der Antrieb, -e",
    "japanese": "原動力、衝動",
    "related": "antreiben (駆動する), treiben (駆り立てる)"
  },
  {
    "word": "insofern",
    "japanese": "その限りにおいて",
    "related": "in (〜において), so (そのように), fern (遠い)"
  },
  {
    "word": "wissenschaftlich",
    "japanese": "科学的な、学問的な",
    "related": "die Wissenschaft (科学), wissen (知る)"
  },
  {
    "word": "die Zuneigung, /",
    "japanese": "愛情、好意",
    "related": "zu (〜へ), neigen (傾く)"
  },
  {
    "word": "die Einschränkung, -en",
    "japanese": "制限",
    "related": "ein (中に), Schranke (柵)"
  },
  {
    "word": "gewährleisten",
    "japanese": "保証する",
    "related": "die Gewähr (保証), leisten (果たす)"
  },
  {
    "word": "bedienen",
    "japanese": "操作する",
    "related": "dienen (仕える), Diener (召使い)"
  },
  {
    "word": "Bestand haben",
    "japanese": "存続する、有効である",
    "related": "bestehen (存在する), stehen (立つ)"
  },
  {
    "word": "die Notwendigkeit",
    "japanese": "必然性",
    "related": "Not (必要、困窮), wenden (向ける), notwendig (必要な)"
  },
  {
    "word": "die Schwäche, -n",
    "japanese": "弱さ",
    "related": "schwach (弱い)"
  },
  {
    "word": "verweisen auf",
    "japanese": "〜を指示する、言及する",
    "related": "weisen (指し示す)"
  },
  {
    "word": "die Kompetenz, -en",
    "japanese": "能力、専門知識",
    "related": "kompetent (有能な)"
  },
  {
    "word": "anknüpfen an + A",
    "japanese": "~と結びつける",
    "related": "der Knopf (ボタン), der Knoten (結び目)"
  },
  {
    "word": "vielfältig",
    "japanese": "多様な",
    "related": "viel (多くの), Falte (折り目)"
  },
  {
    "word": "die Prognose, -n",
    "japanese": "予報",
    "related": "ギリシャ語 pro (前に) + gnosis (知識)"
  },
  {
    "word": "darlegen",
    "japanese": "～を（順序立てて）説明する、詳述する",
    "related": "dar (提示), legen (置く)"
  },
  {
    "word": "bleiben",
    "japanese": "とどまる",
    "related": "übrig bleiben (残る)"
  },
  {
    "word": "von Vorteil / von Nachteil sein",
    "japanese": "有利である/不利である",
    "related": "der Teil (部分)"
  },
  {
    "word": "der Beweis, -e",
    "japanese": "証明、証拠",
    "related": "beweisen (証明する), weisen (指し示す)"
  },
  {
    "word": "ausgewogen",
    "japanese": "バランスの取れた",
    "related": "auswiegen (バランスをとる), die Waage (天秤)"
  },
  {
    "word": "willkürlich",
    "japanese": "任意の、恣意的な",
    "related": "der Wille (意志)"
  },
  {
    "word": "der Umgang, /",
    "japanese": "付き合い、扱い",
    "related": "umgehen mit (〜を扱う), gehen (行く)"
  },
  {
    "word": "übertragen",
    "japanese": "応用する、当てはめる",
    "related": "über (越えて), tragen (運ぶ)"
  },
  {
    "word": "nachvollziehen",
    "japanese": "（論理を）追う、理解する、たどる",
    "related": "nach (後を), voll (完全に), ziehen (引く)"
  },
  {
    "word": "werden",
    "japanese": "～になる、～だろう",
    "related": "(語源的に「向きを変える」の意)"
  },
  {
    "word": "tolerieren",
    "japanese": "容認する",
    "related": "Toleranz (寛容)"
  },
  {
    "word": "verweisen (auf + Akkusativ)",
    "japanese": "～を指示する、参照させる",
    "related": "weisen (指し示す)"
  },
  {
    "word": "sich beziehen (auf + Akkusativ)",
    "japanese": "～に言及する、～と関連する",
    "related": "ziehen (引く)"
  },
  {
    "word": "ein gehen auf",
    "japanese": "~に応じる、言及する",
    "related": "ein (中に), gehen (行く)"
  },
  {
    "word": "die Auffassung",
    "japanese": "見解、解釈",
    "related": "auffassen (理解する), fassen (掴む)"
  },
  {
    "word": "betreffen",
    "japanese": "関係する、~に関するものである、~に当てはまる",
    "related": "treffen (当たる)"
  },
  {
    "word": "hingegen",
    "japanese": "それに対して",
    "related": "hin (そちらへ), gegen (反対に)"
  },
  {
    "word": "ursprünglich",
    "japanese": "本来の、最初の",
    "related": "der Ursprung (起源), springen (跳ぶ)"
  },
  {
    "word": "groß / klein",
    "japanese": "大きい / 小さい",
    "related": "die Größe (大きさ), vergrößern (拡大する) / verkleinern (縮小する)"
  },
  {
    "word": "unbedingt",
    "japanese": "無条件の",
    "related": "un- (否定), bedingen (条件づける)"
  },
  {
    "word": "der Wertgegenstand, -e",
    "japanese": "貴重品",
    "related": "Wert (価値), Gegenstand (物)"
  },
  {
    "word": "veranschaulichen",
    "japanese": "～を（例などで）分かりやすく示す",
    "related": "anschaulich (分かりやすい)"
  },
  {
    "word": "stoische Weise",
    "japanese": "ストア派の賢者",
    "related": "die Stoa (ストア派), weise (賢い)"
  },
  {
    "word": "die Gewissheit",
    "japanese": "確実性",
    "related": "gewiss (確かな), wissen (知る)"
  },
  {
    "word": "besonder",
    "japanese": "特殊的、個別的",
    "related": "sondern (分離する)"
  },
  {
    "word": "sensibel",
    "japanese": "繊細な、機密の",
    "related": "sensitiv (敏感な), Sinn (感覚)"
  },
  {
    "word": "die Sittlichkeit",
    "japanese": "人倫、道徳性",
    "related": "die Sitte (慣習、道徳), sittlich (道徳的な)"
  },
  {
    "word": "allgemein",
    "japanese": "普遍的",
    "related": "all (全て), gemein (共通の)"
  },
  {
    "word": "richtig / falsch",
    "japanese": "正しい / 間違った",
    "related": "das Recht (権利、法), richten (裁く、向ける)"
  },
  {
    "word": "vertreten",
    "japanese": "（意見・立場）を代表する、支持する",
    "related": "treten (歩む、踏む)"
  },
  {
    "word": "die Übereinstimmung, -en",
    "japanese": "一致",
    "related": "überein (一致して), stimmen (合う)"
  },
  {
    "word": "zeigen / aufzeigen",
    "japanese": "～を示す、明らかにする",
    "related": "das Zeichen (しるし)"
  },
  {
    "word": "leistungsfähig",
    "japanese": "能力の高い、高性能の",
    "related": "die Leistung (成果), fähig (能力がある)"
  },
  {
    "word": "erörtern",
    "japanese": "～を論じる、討議する",
    "related": "der Ort (場所)"
  },
  {
    "word": "die Traurigkeit, /",
    "japanese": "悲しみ",
    "related": "traurig (悲しい)"
  }
]
